[
  {
    "Título": "Local en Colinas de San Miguel, Col. Colinas de San Miguel C.P. 66648, Apodaca",
    "Precio": 108000,
    "Ubicación": "Colinas de San Miguel, Col. Colinas de San Miguel C.P. 66648, Apodaca",
    "Superficie": 270,
    "Enlace": "https://propiedades.com/inmuebles/local-en-renta-colinas-de-san-miguel-colinas-de-san-miguel-nuevo_leon-28421607",
    "Lat": "25.7207068",
    "Lng": "-100.1699756"
  },
  {
    "Título": "Local en Mezquital, Col. Santa Rosa C.P. 66604, Apodaca",
    "Precio": 23034,
    "Ubicación": "Mezquital, Col. Santa Rosa C.P. 66604, Apodaca",
    "Superficie": 69,
    "Enlace": "https://propiedades.com/inmuebles/local-en-renta-mezquital-santa-rosa-nuevo_leon-27939430",
    "Lat": "25.7842326000",
    "Lng": "-100.1910443000"
  },
  {
    "Título": "Local en , Col. Apodaca Centro C.P. 66600, Apodaca",
    "Precio": 176400,
    "Ubicación": ", Col. Apodaca Centro C.P. 66600, Apodaca",
    "Superficie": 3528,
    "Enlace": "https://propiedades.com/inmuebles/local-en-renta-apodaca-centro-nuevo_leon-30058102",
    "Lat": "25.7786212000",
    "Lng": "-100.1941399000"
  },
  {
    "Título": "Local en APODACA, Col. Industrial Martel C.P. 66637, Apodaca",
    "Precio": 70000,
    "Ubicación": "APODACA, Col. Industrial Martel C.P. 66637, Apodaca",
    "Superficie": 200,
    "Enlace": "https://propiedades.com/inmuebles/local-en-renta-apodaca-industrial-martel-nuevo_leon-29768650",
    "Lat": "25.77144",
    "Lng": "-100.1683063"
  },
  {
    "Título": "Local en  , Col. Parque Industrial Avante Aeropuerto C.P. 66643, Apodaca",
    "Precio": 50278,
    "Ubicación": " , Col. Parque Industrial Avante Aeropuerto C.P. 66643, Apodaca",
    "Superficie": 157,
    "Enlace": "https://propiedades.com/inmuebles/local-en-renta-parque-industrial-avante-aeropuerto-nuevo_leon-27092444",
    "Lat": "25.7496373",
    "Lng": "-100.1326768"
  },
  {
    "Título": "Local en Avenida Ruiz Cortinez, Col. Los Candiles C.P. 66647, Apodaca",
    "Precio": 24490,
    "Ubicación": "Avenida Ruiz Cortinez, Col. Los Candiles C.P. 66647, Apodaca",
    "Superficie": 195,
    "Enlace": "https://ulises.propiedades.com/inmuebles/local-en-renta-los-candiles-nuevo-leon-27090714",
    "Lat": "25.7118347",
    "Lng": "-100.1608719"
  },
  {
    "Título": "Local en  , Col. Rinconada Colonial C.P. 66606, Apodaca",
    "Precio": 14000,
    "Ubicación": " , Col. Rinconada Colonial C.P. 66606, Apodaca",
    "Superficie": 75,
    "Enlace": "https://propiedades.com/inmuebles/local-en-renta-rinconada-colonial-nuevo_leon-29523117",
    "Lat": "25.7931085645",
    "Lng": "-100.1977678570"
  },
  {
    "Título": "Local en  , Col. Industrial Apodaca C.P. 66614, Apodaca",
    "Precio": 25200,
    "Ubicación": " , Col. Industrial Apodaca C.P. 66614, Apodaca",
    "Superficie": 78,
    "Enlace": "https://propiedades.com/inmuebles/local-en-renta-industrial-apodaca-nuevo_leon-29921417",
    "Lat": "25.7885040000",
    "Lng": "-100.1458760000"
  },
  {
    "Título": "Local en av. concordia #1300, Col. Metroplex C.P. 66612, Apodaca",
    "Precio": 58400,
    "Ubicación": "av. concordia #1300, Col. Metroplex C.P. 66612, Apodaca",
    "Superficie": 120,
    "Enlace": "https://propiedades.com/inmuebles/local-en-renta-av-concordia-1300-metroplex-nuevo_leon-29295704",
    "Lat": "25.7929955840",
    "Lng": "-100.2397349310"
  },
  {
    "Título": "Local en Carretera Santa Rosa Mezquital, Col. Santa Elena 2do. Sector C.P. 66613, Apodaca",
    "Precio": 40000,
    "Ubicación": "Carretera Santa Rosa Mezquital, Col. Santa Elena 2do. Sector C.P. 66613, Apodaca",
    "Superficie": 180,
    "Enlace": "https://propiedades.com/inmuebles/local-en-renta-carretera-santa-rosa-mezquital-santa-elena-2do-sector-nuevo_leon-27316082",
    "Lat": "25.8170248",
    "Lng": "-100.2409292"
  },
  {
    "Título": "Local en , Col. Privadas Borneo C.P. 66632, Apodaca",
    "Precio": 14000,
    "Ubicación": ", Col. Privadas Borneo C.P. 66632, Apodaca",
    "Superficie": 60,
    "Enlace": "https://propiedades.com/inmuebles/local-en-renta-privadas-borneo-nuevo_leon-27744577",
    "Lat": "25.7701739",
    "Lng": "-100.2142324"
  },
  {
    "Título": "Local en Concordia, Col. Apodaca Centro C.P. 66600, Apodaca",
    "Precio": 12500,
    "Ubicación": "Concordia, Col. Apodaca Centro C.P. 66600, Apodaca",
    "Superficie": 49,
    "Enlace": "https://propiedades.com/inmuebles/local-en-renta-concordia-apodaca-centro-nuevo_leon-27801132",
    "Lat": "25.7676334",
    "Lng": "-100.1928214"
  },
  {
    "Título": "Local en FAMSA LOS FRESNOS, Col. Jardines de Apodaca C.P. 66635, Apodaca",
    "Precio": 450000,
    "Ubicación": "FAMSA LOS FRESNOS, Col. Jardines de Apodaca C.P. 66635, Apodaca",
    "Superficie": 1800,
    "Enlace": "https://www.propiedades.com/inmuebles/local-en-renta-jardines-de-apodaca-nuevo-leon-27813040",
    "Lat": "25.7719653",
    "Lng": "-100.2624661"
  },
  {
    "Título": "Local en  , Col. Los Cenizos C.P. 66614, Apodaca",
    "Precio": 14500,
    "Ubicación": " , Col. Los Cenizos C.P. 66614, Apodaca",
    "Superficie": 72,
    "Enlace": "https://propiedades.com/inmuebles/local-en-renta-los-cenizos-nuevo_leon-28611945",
    "Lat": "",
    "Lng": ""
  },
  {
    "Título": "Local en  , Col. Apodaca Centro C.P. 66600, Apodaca",
    "Precio": 100000,
    "Ubicación": " , Col. Apodaca Centro C.P. 66600, Apodaca",
    "Superficie": 870,
    "Enlace": "https://propiedades.com/inmuebles/local-en-renta-apodaca-centro-nuevo_leon-29230913",
    "Lat": "25.7786212000",
    "Lng": "-100.1941399000"
  },
  {
    "Título": "Local en  , Col. Ébanos VI C.P. 66612, Apodaca",
    "Precio": 32000,
    "Ubicación": " , Col. Ébanos VI C.P. 66612, Apodaca",
    "Superficie": 230,
    "Enlace": "https://propiedades.com/inmuebles/local-en-renta-ebanos-vi-nuevo_leon-27730674",
    "Lat": "25.7847249833",
    "Lng": "-100.2419909835"
  },
  {
    "Título": "Local en , Col. Magnolias C.P. 66635, Apodaca",
    "Precio": 360000,
    "Ubicación": ", Col. Magnolias C.P. 66635, Apodaca",
    "Superficie": 1200,
    "Enlace": "https://propiedades.com/inmuebles/local-en-renta-magnolias-nuevo_leon-30093606",
    "Lat": "25.7763800000",
    "Lng": "-100.2574900000"
  },
  {
    "Título": "Local en  , Col. Hacienda Santa Isabel C.P. 66612, Apodaca",
    "Precio": 8000,
    "Ubicación": " , Col. Hacienda Santa Isabel C.P. 66612, Apodaca",
    "Superficie": 35,
    "Enlace": "https://propiedades.com/inmuebles/local-en-renta-hacienda-santa-isabel-nuevo_leon-20571378",
    "Lat": "25.7893426967",
    "Lng": "-100.2485383000"
  },
  {
    "Título": "Local en Treviño, Col. Centro, Apodaca, NL, Col. Nova Apodaca C.P. 66605, Apodaca",
    "Precio": 16000,
    "Ubicación": "Treviño, Col. Centro, Apodaca, NL, Col. Nova Apodaca C.P. 66605, Apodaca",
    "Superficie": 32,
    "Enlace": "https://www.propiedades.com/inmuebles/local-en-renta-nova-apodaca-nuevo-leon-27552462",
    "Lat": "25.7628712",
    "Lng": "-100.2602797"
  },
  {
    "Título": "Local en calle avenida conquistadores, Col. Fresnos VIII C.P. 66636, Apodaca",
    "Precio": 360000,
    "Ubicación": "calle avenida conquistadores, Col. Fresnos VIII C.P. 66636, Apodaca",
    "Superficie": 1200,
    "Enlace": "https://propiedades.com/inmuebles/local-en-renta-calle-avenida-conquistadores-fresnos-viii-nuevo_leon-29009930",
    "Lat": "25.7747925",
    "Lng": "-100.2590168"
  },
  {
    "Título": "Local en , Col. El Milagro C.P. 66634, Apodaca",
    "Precio": 159873,
    "Ubicación": ", Col. El Milagro C.P. 66634, Apodaca",
    "Superficie": 456,
    "Enlace": "https://propiedades.com/inmuebles/local-en-renta-el-milagro-nuevo_leon-29891796",
    "Lat": "25.7455519595",
    "Lng": "-100.2032503720"
  },
  {
    "Título": "Local en  , Col. Hacienda las Margaritas IV C.P. 66647, Apodaca",
    "Precio": 9960,
    "Ubicación": " , Col. Hacienda las Margaritas IV C.P. 66647, Apodaca",
    "Superficie": 27,
    "Enlace": "https://propiedades.com/inmuebles/local-en-renta-hacienda-las-margaritas-iv-nuevo_leon-22199387",
    "Lat": "25.7071442107",
    "Lng": "-100.1575899124"
  },
  {
    "Título": "Local en , Col. Moderno Apodaca I C.P. 66600, Apodaca",
    "Precio": 20000,
    "Ubicación": ", Col. Moderno Apodaca I C.P. 66600, Apodaca",
    "Superficie": 50,
    "Enlace": "https://propiedades.com/inmuebles/local-en-renta-moderno-apodaca-i-nuevo_leon-26676180",
    "Lat": "25.7801907",
    "Lng": "-100.182232"
  },
  {
    "Título": "Local en  , Col. Prados de La Cieneguita C.P. 66636, Apodaca",
    "Precio": 12500,
    "Ubicación": " , Col. Prados de La Cieneguita C.P. 66636, Apodaca",
    "Superficie": 50,
    "Enlace": "https://propiedades.com/inmuebles/local-en-renta-prados-de-la-cieneguita-nuevo_leon-30102392",
    "Lat": "25.7832170000",
    "Lng": "-100.2498952000"
  },
  {
    "Título": "Local en , Col. Parque Industrial Milimex C.P. 66637, Apodaca",
    "Precio": 135000,
    "Ubicación": ", Col. Parque Industrial Milimex C.P. 66637, Apodaca",
    "Superficie": 375,
    "Enlace": "https://propiedades.com/inmuebles/local-en-renta-parque-industrial-milimex-nuevo_leon-29960767",
    "Lat": "25.7524675000",
    "Lng": "-100.1983353000"
  },
  {
    "Título": "Local en Miguel Aleman, Col. Parque Industrial Milimex C.P. 66637, Apodaca",
    "Precio": 135000,
    "Ubicación": "Miguel Aleman, Col. Parque Industrial Milimex C.P. 66637, Apodaca",
    "Superficie": 375,
    "Enlace": "https://propiedades.com/inmuebles/local-en-renta-miguel-aleman-parque-industrial-milimex-nuevo_leon-29913617",
    "Lat": "25.7524675",
    "Lng": "-100.1983353"
  },
  {
    "Título": "Local en , Col. Privadas Borneo C.P. 66632, Apodaca",
    "Precio": 16000,
    "Ubicación": ", Col. Privadas Borneo C.P. 66632, Apodaca",
    "Superficie": 60,
    "Enlace": "https://propiedades.com/inmuebles/local-en-renta-privadas-borneo-nuevo_leon-27744578",
    "Lat": "25.7701739000",
    "Lng": "-100.2142324000"
  },
  {
    "Título": "Local en avenida borneo, Col. Privadas Borneo C.P. 66632, Apodaca",
    "Precio": 16000,
    "Ubicación": "avenida borneo, Col. Privadas Borneo C.P. 66632, Apodaca",
    "Superficie": null,
    "Enlace": "https://propiedades.com/inmuebles/local-en-renta-avenida-borneo-privadas-borneo-nuevo_leon-29009685",
    "Lat": "25.7701837",
    "Lng": "-100.21421"
  },
  {
    "Título": "Local en avenida concordia, Col. Altabrisa Premier C.P. 66604, Apodaca",
    "Precio": 18000,
    "Ubicación": "avenida concordia, Col. Altabrisa Premier C.P. 66604, Apodaca",
    "Superficie": 60,
    "Enlace": "https://propiedades.com/inmuebles/local-en-renta-avenida-concordia-altabrisa-premier-nuevo_leon-29014177",
    "Lat": "25.775958",
    "Lng": "-100.2075467"
  },
  {
    "Título": "Local en Avenida Renaceres, Col. Renaceres Residencial C.P. 66614, Apodaca",
    "Precio": 18000,
    "Ubicación": "Avenida Renaceres, Col. Renaceres Residencial C.P. 66614, Apodaca",
    "Superficie": 190,
    "Enlace": "https://propiedades.com/inmuebles/local-en-renta-avenida-renaceres-renaceres-residencial-nuevo_leon-21720905",
    "Lat": "25.8207149783",
    "Lng": "-100.2402456183"
  },
  {
    "Título": "Local en Camino rancho a los Fernández misión de San Javier #300, Col. Pueblo Nuevo III C.P. 66646, Apodaca",
    "Precio": 250000,
    "Ubicación": "Camino rancho a los Fernández misión de San Javier #300, Col. Pueblo Nuevo III C.P. 66646, Apodaca",
    "Superficie": 100,
    "Enlace": "https://propiedades.com/inmuebles/local-en-renta-camino-rancho-a-los-fernandez-mision-de-san-javier-300-pueblo-nuevo-iii-nuevo_leon-27475072",
    "Lat": "25.741711640740757",
    "Lng": "-100.1565157861797"
  },
  {
    "Título": "Local en  , Col. Apodaca Centro C.P. 66600, Apodaca",
    "Precio": 56458,
    "Ubicación": " , Col. Apodaca Centro C.P. 66600, Apodaca",
    "Superficie": 145,
    "Enlace": "https://propiedades.com/inmuebles/local-en-renta-apodaca-centro-nuevo_leon-24603488",
    "Lat": "25.7786212000",
    "Lng": "-100.1941399000"
  },
  {
    "Título": "Local en  , Col. Parque Industrial Avante Aeropuerto C.P. 66643, Apodaca",
    "Precio": 24928,
    "Ubicación": " , Col. Parque Industrial Avante Aeropuerto C.P. 66643, Apodaca",
    "Superficie": 78,
    "Enlace": "https://propiedades.com/inmuebles/local-en-renta-parque-industrial-avante-aeropuerto-nuevo_leon-24998555",
    "Lat": "25.7496373",
    "Lng": "-100.1326768"
  },
  {
    "Título": "Local en  , Col. Parque Industrial Milimex C.P. 66637, Apodaca",
    "Precio": 276600,
    "Ubicación": " , Col. Parque Industrial Milimex C.P. 66637, Apodaca",
    "Superficie": 800,
    "Enlace": "https://propiedades.com/inmuebles/local-en-renta-parque-industrial-milimex-nuevo_leon-28331027",
    "Lat": "25.7537248000",
    "Lng": "-100.1970261000"
  },
  {
    "Título": "Local en  , Col. Hacienda las Margaritas IV C.P. 66647, Apodaca",
    "Precio": 40507,
    "Ubicación": " , Col. Hacienda las Margaritas IV C.P. 66647, Apodaca",
    "Superficie": 144,
    "Enlace": "https://propiedades.com/inmuebles/local-en-renta-hacienda-las-margaritas-iv-nuevo_leon-22199371",
    "Lat": "25.7071442107",
    "Lng": "-100.1575899124"
  },
  {
    "Título": "Local en Isidoro, Col. Parque Industrial Apodaca C.P. 66633, Apodaca",
    "Precio": 278900,
    "Ubicación": "Isidoro, Col. Parque Industrial Apodaca C.P. 66633, Apodaca",
    "Superficie": 43,
    "Enlace": "https://propiedades.com/inmuebles/local-en-renta-isidoro-parque-industrial-apodaca-nuevo_leon-28811306",
    "Lat": "25.77144",
    "Lng": "-100.1683063"
  },
  {
    "Título": "Local en IRLANDA #s/n, Col. Las Palmas C.P. 66610, Apodaca",
    "Precio": 120000,
    "Ubicación": "IRLANDA #s/n, Col. Las Palmas C.P. 66610, Apodaca",
    "Superficie": 628,
    "Enlace": "https://propiedades.com/inmuebles/local-en-renta-irlanda-sn-las-palmas-nuevo_leon-29802591",
    "Lat": "25.7810396",
    "Lng": "-100.2661371"
  },
  {
    "Título": "Local en  , Col. Hacienda las Margaritas IV C.P. 66647, Apodaca",
    "Precio": 10488,
    "Ubicación": " , Col. Hacienda las Margaritas IV C.P. 66647, Apodaca",
    "Superficie": 27,
    "Enlace": "https://propiedades.com/inmuebles/local-en-renta-hacienda-las-margaritas-iv-nuevo_leon-26782989",
    "Lat": "25.7071442107",
    "Lng": "-100.1575899124"
  },
  {
    "Título": "Local en  , Col. Metroplex C.P. 66612, Apodaca",
    "Precio": 28200,
    "Ubicación": " , Col. Metroplex C.P. 66612, Apodaca",
    "Superficie": 120,
    "Enlace": "https://propiedades.com/inmuebles/local-en-renta-metroplex-nuevo_leon-19138710",
    "Lat": "25.7861199000",
    "Lng": "-100.2477005000"
  },
  {
    "Título": "Local en San Javier #800, Col. San Javier C.P. 66646, Apodaca",
    "Precio": 5000,
    "Ubicación": "San Javier #800, Col. San Javier C.P. 66646, Apodaca",
    "Superficie": 32,
    "Enlace": "https://propiedades.com/inmuebles/local-en-renta-san-javier-800-san-javier-nuevo_leon-29760851",
    "Lat": "25.745932",
    "Lng": "-100.1520081"
  },
  {
    "Título": "Local en  , Col. Prados de Santa Rosa C.P. 66610, Apodaca",
    "Precio": 6000,
    "Ubicación": " , Col. Prados de Santa Rosa C.P. 66610, Apodaca",
    "Superficie": 14,
    "Enlace": "https://propiedades.com/inmuebles/local-en-renta-prados-de-santa-rosa-nuevo_leon-28270991",
    "Lat": "25.7942287896",
    "Lng": "-100.2245093338"
  },
  {
    "Título": "Local en Av Chopo #532, Col. Bosque Real II C.P. 66612, Apodaca",
    "Precio": 10000,
    "Ubicación": "Av Chopo #532, Col. Bosque Real II C.P. 66612, Apodaca",
    "Superficie": 90,
    "Enlace": "https://propiedades.com/inmuebles/local-en-renta-av-chopo-532-bosque-real-ii-nuevo_leon-30067565",
    "Lat": "25.7805115",
    "Lng": "-100.2440359"
  },
  {
    "Título": "Local en ignacio zaragoza #219, Col. Ciudad Apodaca Centro C.P. 66600, Apodaca",
    "Precio": 34710,
    "Ubicación": "ignacio zaragoza #219, Col. Ciudad Apodaca Centro C.P. 66600, Apodaca",
    "Superficie": 107,
    "Enlace": "https://propiedades.com/inmuebles/local-en-renta-ignacio-zaragoza-219-ciudad-apodaca-centro-nuevo_leon-27146677",
    "Lat": "25.7823591000",
    "Lng": "-100.1892356000"
  },
  {
    "Título": "Local en  , Col. Futuro Apodaca C.P. 66600, Apodaca",
    "Precio": 53390,
    "Ubicación": " , Col. Futuro Apodaca C.P. 66600, Apodaca",
    "Superficie": 283,
    "Enlace": "https://propiedades.com/inmuebles/local-en-renta-futuro-apodaca-nuevo_leon-28141753",
    "Lat": "25.7467642988",
    "Lng": "-100.1968424782"
  },
  {
    "Título": "Local en concordia #1300, Col. Hacienda Santa Isabel C.P. 66612, Apodaca",
    "Precio": 28200,
    "Ubicación": "concordia #1300, Col. Hacienda Santa Isabel C.P. 66612, Apodaca",
    "Superficie": 120,
    "Enlace": "https://propiedades.com/inmuebles/local-en-renta-concordia-1300-hacienda-santa-isabel-nuevo_leon-28528577",
    "Lat": "25.7919323860",
    "Lng": "-100.2582355460"
  },
  {
    "Título": "Local en Avenida Héctor Caballero, Col. Noria Norte C.P. 66633, Apodaca",
    "Precio": 7000,
    "Ubicación": "Avenida Héctor Caballero, Col. Noria Norte C.P. 66633, Apodaca",
    "Superficie": 40,
    "Enlace": "https://propiedades.com/inmuebles/local-en-renta-avenida-hector-caballero-noria-norte-nuevo_leon-29905603",
    "Lat": "25.7380659420",
    "Lng": "-100.1916301380"
  },
  {
    "Título": "Local en abasolo, Col. Valle de Apodaca IV C.P. 66612, Apodaca",
    "Precio": 25000,
    "Ubicación": "abasolo, Col. Valle de Apodaca IV C.P. 66612, Apodaca",
    "Superficie": null,
    "Enlace": "https://propiedades.com/inmuebles/local-en-renta-abasolo-valle-de-apodaca-iv-nuevo_leon-29009800",
    "Lat": "25.7812443000",
    "Lng": "-100.1805862000"
  }
]