[
  {
    "Título": "Local en  , Col. Unidad Nacional C.P. 89410, Ciudad Madero",
    "Precio": 11500,
    "Ubicación": " , Col. Unidad Nacional C.P. 89410, Ciudad Madero",
    "Superficie": 55,
    "Enlace": "https://propiedades.com/inmuebles/local-en-renta-unidad-nacional-tamaulipas-27098858",
    "Lat": "22.2716655807",
    "Lng": "-97.8471888904"
  },
  {
    "Título": "Local en  , Col. Unidad Nacional C.P. 89410, Ciudad Madero",
    "Precio": 20000,
    "Ubicación": " , Col. Unidad Nacional C.P. 89410, Ciudad Madero",
    "Superficie": 36,
    "Enlace": "https://propiedades.com/inmuebles/local-en-renta-unidad-nacional-tamaulipas-25218304",
    "Lat": "22.2690380000",
    "Lng": "-97.8467304000"
  },
  {
    "Título": "Local en  , Col. Hidalgo Oriente C.P. 89570, Ciudad Madero",
    "Precio": 4700,
    "Ubicación": " , Col. Hidalgo Oriente C.P. 89570, Ciudad Madero",
    "Superficie": 47,
    "Enlace": "https://propiedades.com/inmuebles/local-en-renta-hidalgo-oriente-tamaulipas-24402847",
    "Lat": "22.2542094000",
    "Lng": "-97.8218387000"
  },
  {
    "Título": "Local en  , Col. Hipódromo C.P. 89560, Ciudad Madero",
    "Precio": 35000,
    "Ubicación": " , Col. Hipódromo C.P. 89560, Ciudad Madero",
    "Superficie": 200,
    "Enlace": "https://propiedades.com/inmuebles/local-en-renta-hipodromo-tamaulipas-28970282",
    "Lat": "22.2658996000",
    "Lng": "-97.8251546000"
  },
  {
    "Título": "Local en , Col. Ampliación Unidad Nacional C.P. 89510, Ciudad Madero",
    "Precio": 18000,
    "Ubicación": ", Col. Ampliación Unidad Nacional C.P. 89510, Ciudad Madero",
    "Superficie": null,
    "Enlace": "https://propiedades.com/inmuebles/local-en-renta-ampliacion-unidad-nacional-tamaulipas-29973370",
    "Lat": "22.2825183139",
    "Lng": "-97.8425895466"
  },
  {
    "Título": "Local en Carranza, Col. 1° de Mayo C.P. 89450, Ciudad Madero",
    "Precio": 15000,
    "Ubicación": "Carranza, Col. 1° de Mayo C.P. 89450, Ciudad Madero",
    "Superficie": 51,
    "Enlace": "https://propiedades.com/inmuebles/local-en-renta-carranza-1-de-mayo-tamaulipas-28177640",
    "Lat": "22.2475000000",
    "Lng": "-97.8384000000"
  },
  {
    "Título": "Local en Nicolas Bravo 604 #604, Col. Hipódromo C.P. 89560, Ciudad Madero",
    "Precio": 5500,
    "Ubicación": "Nicolas Bravo 604 #604, Col. Hipódromo C.P. 89560, Ciudad Madero",
    "Superficie": 30,
    "Enlace": "https://propiedades.com/inmuebles/local-en-renta-nicolas-bravo-604-604-hipodromo-tamaulipas-26998902",
    "Lat": "22.26408746993574",
    "Lng": "-97.82588451479083"
  },
  {
    "Título": "Local en  , Col. Jardín 20 de Noviembre C.P. 89440, Ciudad Madero",
    "Precio": 4000,
    "Ubicación": " , Col. Jardín 20 de Noviembre C.P. 89440, Ciudad Madero",
    "Superficie": 24,
    "Enlace": "https://propiedades.com/inmuebles/local-en-renta-jardin-20-de-noviembre-tamaulipas-27162046",
    "Lat": "22.2644692911",
    "Lng": "-97.8525006381"
  },
  {
    "Título": "Local en  , Col. Unidad Nacional C.P. 89410, Ciudad Madero",
    "Precio": 7800,
    "Ubicación": " , Col. Unidad Nacional C.P. 89410, Ciudad Madero",
    "Superficie": 31,
    "Enlace": "https://propiedades.com/inmuebles/local-en-renta-unidad-nacional-tamaulipas-29987134",
    "Lat": "22.2728357000",
    "Lng": "-97.8520853000"
  },
  {
    "Título": "Local en  , Col. Jardín 20 de Noviembre C.P. 89440, Ciudad Madero",
    "Precio": 18500,
    "Ubicación": " , Col. Jardín 20 de Noviembre C.P. 89440, Ciudad Madero",
    "Superficie": null,
    "Enlace": "https://propiedades.com/inmuebles/local-en-renta-jardin-20-de-noviembre-tamaulipas-28038628",
    "Lat": "22.2608083000",
    "Lng": "-97.8537954000"
  },
  {
    "Título": "Local en  , Col. Hidalgo Oriente C.P. 89570, Ciudad Madero",
    "Precio": 2500,
    "Ubicación": " , Col. Hidalgo Oriente C.P. 89570, Ciudad Madero",
    "Superficie": null,
    "Enlace": "https://propiedades.com/inmuebles/local-en-renta-hidalgo-oriente-tamaulipas-28247363",
    "Lat": "22.2533737988",
    "Lng": "-97.8224372864"
  },
  {
    "Título": "Local en  , Col. Jardín 20 de Noviembre C.P. 89440, Ciudad Madero",
    "Precio": 4900,
    "Ubicación": " , Col. Jardín 20 de Noviembre C.P. 89440, Ciudad Madero",
    "Superficie": 27,
    "Enlace": "https://propiedades.com/inmuebles/local-en-renta-jardin-20-de-noviembre-tamaulipas-27181302",
    "Lat": "22.2644519154",
    "Lng": "-97.8525220957"
  },
  {
    "Título": "Local en  , Col. Ciudad Madero Centro C.P. 89400, Ciudad Madero",
    "Precio": 45000,
    "Ubicación": " , Col. Ciudad Madero Centro C.P. 89400, Ciudad Madero",
    "Superficie": 254,
    "Enlace": "https://propiedades.com/inmuebles/local-en-renta-ciudad-madero-centro-tamaulipas-17799528",
    "Lat": "22.2454459",
    "Lng": "-97.8347556"
  },
  {
    "Título": "Local en PROL 1 DE MAYO, Col. Loma Del Gallo C.P. 89460, Ciudad Madero",
    "Precio": 16000,
    "Ubicación": "PROL 1 DE MAYO, Col. Loma Del Gallo C.P. 89460, Ciudad Madero",
    "Superficie": 100,
    "Enlace": "https://propiedades.com/inmuebles/local-en-renta-prol-1-de-mayo-loma-del-gallo-tamaulipas-18442787",
    "Lat": "22.2560584",
    "Lng": "-97.8527302"
  },
  {
    "Título": "Local en , Col. Las Américas C.P. 89420, Ciudad Madero",
    "Precio": 10000,
    "Ubicación": ", Col. Las Américas C.P. 89420, Ciudad Madero",
    "Superficie": 60,
    "Enlace": "https://propiedades.com/inmuebles/local-en-renta-las-americas-tamaulipas-29877717",
    "Lat": "22.2725835000",
    "Lng": "-97.8551556000"
  },
  {
    "Título": "Local en HIDALGO, Col. Unidad Nacional C.P. 89410, Ciudad Madero",
    "Precio": 8500,
    "Ubicación": "HIDALGO, Col. Unidad Nacional C.P. 89410, Ciudad Madero",
    "Superficie": 58,
    "Enlace": "https://propiedades.com/inmuebles/local-en-renta-hidalgo-unidad-nacional-tamaulipas-27523339",
    "Lat": "22.2425028",
    "Lng": "-97.8484535"
  },
  {
    "Título": "Local en Ave. Álvaro Obregón, Col. Hidalgo Oriente C.P. 89570, Ciudad Madero",
    "Precio": 5100,
    "Ubicación": "Ave. Álvaro Obregón, Col. Hidalgo Oriente C.P. 89570, Ciudad Madero",
    "Superficie": 43,
    "Enlace": "https://propiedades.com/inmuebles/local-en-renta-ave-alvaro-obregon-hidalgo-oriente-tamaulipas-28177434",
    "Lat": "22.2562000000",
    "Lng": "-97.8271000000"
  },
  {
    "Título": "Local en Brasil esquina con 18 de marzo col. Lázaro cardenas #1100, Col. Lázaro Cárdenas C.P. 89430, Ciudad Madero",
    "Precio": 40000,
    "Ubicación": "Brasil esquina con 18 de marzo col. Lázaro cardenas #1100, Col. Lázaro Cárdenas C.P. 89430, Ciudad Madero",
    "Superficie": 210,
    "Enlace": "https://propiedades.com/inmuebles/local-en-renta-brasil-esquina-con-18-de-marzo-col-lazaro-cardenas-1100-lazaro-cardenas-tamaulipas-29116280",
    "Lat": "22.2568936000",
    "Lng": "-97.8429149000"
  },
  {
    "Título": "Local en V #1, Col. Ciudad Madero Centro C.P. 89400, Ciudad Madero",
    "Precio": 5000,
    "Ubicación": "V #1, Col. Ciudad Madero Centro C.P. 89400, Ciudad Madero",
    "Superficie": 59,
    "Enlace": "https://propiedades.com/inmuebles/local-en-renta-v-1-ciudad-madero-centro-tamaulipas-28859435",
    "Lat": "22.2454459",
    "Lng": "-97.8347556"
  },
  {
    "Título": "Local en  , Col. Ciudad Madero Centro C.P. 89400, Ciudad Madero",
    "Precio": 70000,
    "Ubicación": " , Col. Ciudad Madero Centro C.P. 89400, Ciudad Madero",
    "Superficie": 184,
    "Enlace": "https://propiedades.com/inmuebles/local-en-renta-ciudad-madero-centro-tamaulipas-27882118",
    "Lat": "22.2470937000",
    "Lng": "-97.8358770000"
  },
  {
    "Título": "Local en Francisco Villa, Col. 15 de Mayo C.P. 89519, Ciudad Madero",
    "Precio": 49000,
    "Ubicación": "Francisco Villa, Col. 15 de Mayo C.P. 89519, Ciudad Madero",
    "Superficie": null,
    "Enlace": "https://propiedades.com/inmuebles/local-en-renta-francisco-villa-15-de-mayo-tamaulipas-28689445",
    "Lat": "22.3064000000",
    "Lng": "-97.8436000000"
  },
  {
    "Título": "Local en  , Col. Unidad Nacional C.P. 89410, Ciudad Madero",
    "Precio": 19999,
    "Ubicación": " , Col. Unidad Nacional C.P. 89410, Ciudad Madero",
    "Superficie": 100,
    "Enlace": "https://propiedades.com/inmuebles/local-en-renta-unidad-nacional-tamaulipas-27428848",
    "Lat": "22.2706593",
    "Lng": "-97.84903500000001"
  },
  {
    "Título": "Local en  , Col. 1° de Mayo C.P. 89450, Ciudad Madero",
    "Precio": 30000,
    "Ubicación": " , Col. 1° de Mayo C.P. 89450, Ciudad Madero",
    "Superficie": 200,
    "Enlace": "https://propiedades.com/inmuebles/local-en-renta-1-de-mayo-tamaulipas-28043856",
    "Lat": "22.2423595000",
    "Lng": "-97.8400069000"
  },
  {
    "Título": "Local en plaza caralinda, Col. Las Américas C.P. 89420, Ciudad Madero",
    "Precio": 18000,
    "Ubicación": "plaza caralinda, Col. Las Américas C.P. 89420, Ciudad Madero",
    "Superficie": 100,
    "Enlace": "https://propiedades.com/inmuebles/local-en-renta-plaza-caralinda-las-americas-tamaulipas-29377496",
    "Lat": "22.2744766000",
    "Lng": "-97.8554479000"
  },
  {
    "Título": "Local en , Col. Las Américas C.P. 89420, Ciudad Madero",
    "Precio": 6000,
    "Ubicación": ", Col. Las Américas C.P. 89420, Ciudad Madero",
    "Superficie": 24,
    "Enlace": "https://propiedades.com/inmuebles/local-en-renta-las-americas-tamaulipas-29822256",
    "Lat": "22.2708231000",
    "Lng": "-97.8545283000"
  },
  {
    "Título": "Local en  , Col. Ciudad Madero Centro C.P. 89400, Ciudad Madero",
    "Precio": 20000,
    "Ubicación": " , Col. Ciudad Madero Centro C.P. 89400, Ciudad Madero",
    "Superficie": 222,
    "Enlace": "https://propiedades.com/inmuebles/local-en-renta-ciudad-madero-centro-tamaulipas-27927237",
    "Lat": "22.2470937000",
    "Lng": "-97.8358770000"
  },
  {
    "Título": "Local en Brasil #1100, Col. Lázaro Cárdenas C.P. 89430, Ciudad Madero",
    "Precio": 40000,
    "Ubicación": "Brasil #1100, Col. Lázaro Cárdenas C.P. 89430, Ciudad Madero",
    "Superficie": 210,
    "Enlace": "https://propiedades.com/inmuebles/local-en-renta-brasil-1100-lazaro-cardenas-tamaulipas-29137349",
    "Lat": "22.2552115860",
    "Lng": "-97.8407906040"
  },
  {
    "Título": "Local en Jimenez, Col. Lucio Blanco Ampliación los Pinos C.P. 89513, Ciudad Madero",
    "Precio": 18000,
    "Ubicación": "Jimenez, Col. Lucio Blanco Ampliación los Pinos C.P. 89513, Ciudad Madero",
    "Superficie": 130,
    "Enlace": "https://propiedades.com/inmuebles/local-en-renta-jimenez-lucio-blanco-ampliacion-los-pinos-tamaulipas-28845919",
    "Lat": "22.2688088",
    "Lng": "-97.8279527"
  },
  {
    "Título": "Local en  , Col. Unidad Nacional C.P. 89410, Ciudad Madero",
    "Precio": 9500,
    "Ubicación": " , Col. Unidad Nacional C.P. 89410, Ciudad Madero",
    "Superficie": 30,
    "Enlace": "https://propiedades.com/inmuebles/local-en-renta-unidad-nacional-tamaulipas-29981612",
    "Lat": "22.2722052000",
    "Lng": "-97.8476749000"
  },
  {
    "Título": "Local en  , Col. Unidad Nacional C.P. 89410, Ciudad Madero",
    "Precio": 10500,
    "Ubicación": " , Col. Unidad Nacional C.P. 89410, Ciudad Madero",
    "Superficie": 26,
    "Enlace": "https://propiedades.com/inmuebles/local-en-renta-unidad-nacional-tamaulipas-27990240",
    "Lat": "22.2722052000",
    "Lng": "-97.8476749000"
  },
  {
    "Título": "Local en  , Col. Unidad Nacional C.P. 89410, Ciudad Madero",
    "Precio": 8000,
    "Ubicación": " , Col. Unidad Nacional C.P. 89410, Ciudad Madero",
    "Superficie": 41,
    "Enlace": "https://propiedades.com/inmuebles/local-en-renta-unidad-nacional-tamaulipas-29372154",
    "Lat": "22.2716889224",
    "Lng": "-97.8469185171"
  },
  {
    "Título": "Local en  , Col. Las Américas C.P. 89420, Ciudad Madero",
    "Precio": 20000,
    "Ubicación": " , Col. Las Américas C.P. 89420, Ciudad Madero",
    "Superficie": 125,
    "Enlace": "https://propiedades.com/inmuebles/local-en-renta-las-americas-tamaulipas-27075628",
    "Lat": "22.2744031000",
    "Lng": "-97.8553953000"
  },
  {
    "Título": "Local en  , Col. Unidad Nacional C.P. 89410, Ciudad Madero",
    "Precio": 12000,
    "Ubicación": " , Col. Unidad Nacional C.P. 89410, Ciudad Madero",
    "Superficie": 49,
    "Enlace": "https://propiedades.com/inmuebles/local-en-renta-unidad-nacional-tamaulipas-29369291",
    "Lat": "22.2716889224",
    "Lng": "-97.8469077882"
  },
  {
    "Título": "Local en Av Jalisco #200.\n, Col. Monteverde C.P. 89420, Ciudad Madero",
    "Precio": 5000,
    "Ubicación": "Av Jalisco #200.\n, Col. Monteverde C.P. 89420, Ciudad Madero",
    "Superficie": null,
    "Enlace": "https://www.propiedades.com/inmuebles/local-en-renta-av-jalisco-200\n-monteverde-tamaulipas-29937110",
    "Lat": "22.276882",
    "Lng": "-97.8375474"
  },
  {
    "Título": "Local en Allende #308, Col. 1° de Mayo C.P. 89450, Ciudad Madero",
    "Precio": 25000,
    "Ubicación": "Allende #308, Col. 1° de Mayo C.P. 89450, Ciudad Madero",
    "Superficie": 320,
    "Enlace": "https://propiedades.com/inmuebles/local-en-renta-allende-308-1-de-mayo-tamaulipas-29116138",
    "Lat": "22.2472397",
    "Lng": "-97.8435949"
  },
  {
    "Título": "Local en  , Col. Frente Democrático C.P. 89470, Ciudad Madero",
    "Precio": 23000,
    "Ubicación": " , Col. Frente Democrático C.P. 89470, Ciudad Madero",
    "Superficie": null,
    "Enlace": "https://propiedades.com/inmuebles/local-en-renta-frente-democratico-tamaulipas-30081180",
    "Lat": "22.2460851000",
    "Lng": "-97.8560057000"
  },
  {
    "Título": "Local en  , Col. Unidad Nacional C.P. 89410, Ciudad Madero",
    "Precio": 14000,
    "Ubicación": " , Col. Unidad Nacional C.P. 89410, Ciudad Madero",
    "Superficie": 96,
    "Enlace": "https://propiedades.com/inmuebles/local-en-renta-unidad-nacional-tamaulipas-29444927",
    "Lat": "22.2722052000",
    "Lng": "-97.8476749000"
  },
  {
    "Título": "Local en  , Col. Del Maestro C.P. 89550, Ciudad Madero",
    "Precio": 14000,
    "Ubicación": " , Col. Del Maestro C.P. 89550, Ciudad Madero",
    "Superficie": 48,
    "Enlace": "https://propiedades.com/inmuebles/local-en-renta-del-maestro-tamaulipas-30013987",
    "Lat": "22.2632359000",
    "Lng": "-97.8408033000"
  },
  {
    "Título": "Local en , Col. Unidad Nacional C.P. 89410, Ciudad Madero",
    "Precio": 10500,
    "Ubicación": ", Col. Unidad Nacional C.P. 89410, Ciudad Madero",
    "Superficie": 28,
    "Enlace": "https://propiedades.com/inmuebles/local-en-renta-unidad-nacional-tamaulipas-29137369",
    "Lat": "",
    "Lng": ""
  },
  {
    "Título": "Local en  , Col. Villas del Mar C.P. 89515, Ciudad Madero",
    "Precio": 12000,
    "Ubicación": " , Col. Villas del Mar C.P. 89515, Ciudad Madero",
    "Superficie": 105,
    "Enlace": "https://propiedades.com/inmuebles/local-en-renta-villas-del-mar-tamaulipas-28703009",
    "Lat": "22.2784217000",
    "Lng": "-97.7971789000"
  },
  {
    "Título": "Local en , Col. Ciudad Madero Centro C.P. 89400, Ciudad Madero",
    "Precio": 6500,
    "Ubicación": ", Col. Ciudad Madero Centro C.P. 89400, Ciudad Madero",
    "Superficie": null,
    "Enlace": "https://propiedades.com/inmuebles/local-en-renta-ciudad-madero-centro-tamaulipas-29894611",
    "Lat": "22.2798981000",
    "Lng": "-97.8415999000"
  },
  {
    "Título": "Local en , Col. Ciudad Madero Centro C.P. 89400, Ciudad Madero",
    "Precio": 6000,
    "Ubicación": ", Col. Ciudad Madero Centro C.P. 89400, Ciudad Madero",
    "Superficie": null,
    "Enlace": "https://propiedades.com/inmuebles/local-en-renta-ciudad-madero-centro-tamaulipas-29894612",
    "Lat": "22.2454459000",
    "Lng": "-97.8347556000"
  },
  {
    "Título": "Local en Chiapas, Col. Unidad Nacional C.P. 89410, Ciudad Madero",
    "Precio": 4500,
    "Ubicación": "Chiapas, Col. Unidad Nacional C.P. 89410, Ciudad Madero",
    "Superficie": 50,
    "Enlace": "https://propiedades.com/inmuebles/local-en-renta-chiapas-unidad-nacional-tamaulipas-28298662",
    "Lat": "22.2659000000",
    "Lng": "-97.8447000000"
  },
  {
    "Título": "Local en  , Col. Ampliación Unidad Nacional C.P. 89510, Ciudad Madero",
    "Precio": 40000,
    "Ubicación": " , Col. Ampliación Unidad Nacional C.P. 89510, Ciudad Madero",
    "Superficie": 198,
    "Enlace": "https://propiedades.com/inmuebles/local-en-renta-ampliacion-unidad-nacional-tamaulipas-17799544",
    "Lat": "22.2755424000",
    "Lng": "-97.8457356000"
  },
  {
    "Título": "Local en  , Col. Las Américas C.P. 89420, Ciudad Madero",
    "Precio": 12000,
    "Ubicación": " , Col. Las Américas C.P. 89420, Ciudad Madero",
    "Superficie": 62,
    "Enlace": "https://propiedades.com/inmuebles/local-en-renta-las-americas-tamaulipas-29933491",
    "Lat": "22.2725835000",
    "Lng": "-97.8551556000"
  },
  {
    "Título": "Local en Allende, Col. 1° de Mayo C.P. 89450, Ciudad Madero",
    "Precio": 12000,
    "Ubicación": "Allende, Col. 1° de Mayo C.P. 89450, Ciudad Madero",
    "Superficie": null,
    "Enlace": "https://propiedades.com/inmuebles/local-en-renta-allende-1-de-mayo-tamaulipas-28174606",
    "Lat": "22.2477000000",
    "Lng": "-97.8378000000"
  },
  {
    "Título": "Local en Ave. Jalisco, Col. Unidad Nacional C.P. 89410, Ciudad Madero",
    "Precio": 10000,
    "Ubicación": "Ave. Jalisco, Col. Unidad Nacional C.P. 89410, Ciudad Madero",
    "Superficie": 50,
    "Enlace": "https://propiedades.com/inmuebles/local-en-renta-ave-jalisco-unidad-nacional-tamaulipas-27598670",
    "Lat": "22.2758000000",
    "Lng": "-97.8511000000"
  }
]