[
  {
    "Título": "Local en Calle Corregidora 1202 #1202, Col. Picasso C.P. 25714, Monclova",
    "Precio": 6500,
    "Ubicación": "Calle Corregidora 1202 #1202, Col. Picasso C.P. 25714, Monclova",
    "Superficie": null,
    "Enlace": "https://propiedades.com/inmuebles/local-en-renta-calle-corregidora-1202-1202-picasso-coahuila-27959409",
    "Lat": "26.920804799032",
    "Lng": "-101.435232060698"
  },
  {
    "Título": "Local en jamaica #41, Col. Guadalupe C.P. 25750, Monclova",
    "Precio": 20000,
    "Ubicación": "jamaica #41, Col. Guadalupe C.P. 25750, Monclova",
    "Superficie": 333,
    "Enlace": "https://propiedades.com/inmuebles/local-en-renta-jamaica-41-guadalupe-coahuila-30061263",
    "Lat": "26.9112656",
    "Lng": "-101.4365535"
  },
  {
    "Título": "Local en Guadalupe Norte #0, Col. Guadalupe Norte C.P. 25720, Monclova",
    "Precio": 11634,
    "Ubicación": "Guadalupe Norte #0, Col. Guadalupe Norte C.P. 25720, Monclova",
    "Superficie": 116,
    "Enlace": "https://propiedades.com/inmuebles/local-en-renta-guadalupe-norte-guadalupe-norte-coahuila-30105219",
    "Lat": "26.9237217",
    "Lng": "-101.4268174"
  },
  {
    "Título": "Local en C Ocampo #500, Col. Monclova Centro C.P. 25700, Monclova",
    "Precio": 8000,
    "Ubicación": "C Ocampo #500, Col. Monclova Centro C.P. 25700, Monclova",
    "Superficie": 75,
    "Enlace": "https://propiedades.com/inmuebles/local-en-renta-c-ocampo-500-monclova-centro-coahuila-28238902",
    "Lat": "26.8957725901689",
    "Lng": "-101.42025820370483"
  },
  {
    "Título": "Local en Guadalupe Norte #0, Col. Guadalupe Norte C.P. 25720, Monclova",
    "Precio": 8282,
    "Ubicación": "Guadalupe Norte #0, Col. Guadalupe Norte C.P. 25720, Monclova",
    "Superficie": 84,
    "Enlace": "https://propiedades.com/inmuebles/local-en-renta-guadalupe-norte-guadalupe-norte-coahuila-30105222",
    "Lat": "26.9237217",
    "Lng": "-101.4268174"
  },
  {
    "Título": "Local en Abasolo, Col. Monclova Centro C.P. 25700, Monclova",
    "Precio": 120000,
    "Ubicación": "Abasolo, Col. Monclova Centro C.P. 25700, Monclova",
    "Superficie": 1104,
    "Enlace": "https://propiedades.com/inmuebles/local-en-renta-abasolo-monclova-centro-coahuila-28294150",
    "Lat": "26.8977882000",
    "Lng": "-101.4182569000"
  },
  {
    "Título": "Local en Guadalupe Norte #0, Col. Guadalupe Norte C.P. 25720, Monclova",
    "Precio": 7888,
    "Ubicación": "Guadalupe Norte #0, Col. Guadalupe Norte C.P. 25720, Monclova",
    "Superficie": 78,
    "Enlace": "https://propiedades.com/inmuebles/local-en-renta-guadalupe-norte-guadalupe-norte-coahuila-30105217",
    "Lat": "26.9237217",
    "Lng": "-101.4268174"
  },
  {
    "Título": "Local en Guadalupe Norte #0, Col. Guadalupe Norte C.P. 25720, Monclova",
    "Precio": 7609,
    "Ubicación": "Guadalupe Norte #0, Col. Guadalupe Norte C.P. 25720, Monclova",
    "Superficie": 82,
    "Enlace": "https://propiedades.com/inmuebles/local-en-renta-guadalupe-norte-guadalupe-norte-coahuila-30105218",
    "Lat": "26.9237217",
    "Lng": "-101.4268174"
  },
  {
    "Título": "Local en  , Col. Monclova Centro C.P. 25700, Monclova",
    "Precio": 58080,
    "Ubicación": " , Col. Monclova Centro C.P. 25700, Monclova",
    "Superficie": 242,
    "Enlace": "https://propiedades.com/inmuebles/local-en-renta-monclova-centro-coahuila-28330992",
    "Lat": "26.8870602000",
    "Lng": "-101.4183197000"
  },
  {
    "Título": "Local en Guadalupe Norte #0, Col. Guadalupe Norte C.P. 25720, Monclova",
    "Precio": 79344,
    "Ubicación": "Guadalupe Norte #0, Col. Guadalupe Norte C.P. 25720, Monclova",
    "Superficie": 750,
    "Enlace": "https://propiedades.com/inmuebles/local-en-renta-guadalupe-norte-guadalupe-norte-coahuila-30105220",
    "Lat": "26.9237217",
    "Lng": "-101.4268174"
  },
  {
    "Título": "Local en  , Col. Monclova Centro C.P. 25700, Monclova",
    "Precio": 168240,
    "Ubicación": " , Col. Monclova Centro C.P. 25700, Monclova",
    "Superficie": 701,
    "Enlace": "https://propiedades.com/inmuebles/local-en-renta-monclova-centro-coahuila-29826587",
    "Lat": "26.9313730000",
    "Lng": "-101.3848603000"
  },
  {
    "Título": "Local en BLVD. HAROLD PAPE, Col. Jardines del Valle C.P. 25730, Monclova",
    "Precio": 15908,
    "Ubicación": "BLVD. HAROLD PAPE, Col. Jardines del Valle C.P. 25730, Monclova",
    "Superficie": 39,
    "Enlace": "https://propiedades.com/inmuebles/local-en-renta-blvd-harold-pape-jardines-del-valle-coahuila-24741615",
    "Lat": "26.9317077",
    "Lng": "-101.4155951"
  },
  {
    "Título": "Local en blvd. Harold Pape, Col. Jardines del Valle C.P. 25730, Monclova",
    "Precio": 19885,
    "Ubicación": "blvd. Harold Pape, Col. Jardines del Valle C.P. 25730, Monclova",
    "Superficie": 39,
    "Enlace": "https://propiedades.com/inmuebles/local-en-renta-blvd-harold-pape-jardines-del-valle-coahuila-24741613",
    "Lat": "26.9317077",
    "Lng": "-101.4155951"
  },
  {
    "Título": "Local en Calle Miguel Blanco  OTE #121, Col. Monclova Centro C.P. 25700, Monclova",
    "Precio": 5500,
    "Ubicación": "Calle Miguel Blanco  OTE #121, Col. Monclova Centro C.P. 25700, Monclova",
    "Superficie": null,
    "Enlace": "https://propiedades.com/inmuebles/local-en-renta-calle-miguel-blanco-ote-121-monclova-centro-coahuila-28112955",
    "Lat": "26.901193282987",
    "Lng": "-101.423011329688"
  },
  {
    "Título": "Local en Blvd. Harold R. Pape Esq. Con Juárez, Col. Palma C.P. 25730, Monclova",
    "Precio": 15000,
    "Ubicación": "Blvd. Harold R. Pape Esq. Con Juárez, Col. Palma C.P. 25730, Monclova",
    "Superficie": 82,
    "Enlace": "https://propiedades.com/inmuebles/local-en-renta-blvd-harold-r-pape-esq-con-juarez-palma-coahuila-16511922",
    "Lat": "",
    "Lng": ""
  },
  {
    "Título": "Local en Calle de la Fuente 235 #235Int. A, Col. Monclova Centro C.P. 25700, Monclova",
    "Precio": 19000,
    "Ubicación": "Calle de la Fuente 235 #235Int. A, Col. Monclova Centro C.P. 25700, Monclova",
    "Superficie": 145,
    "Enlace": "https://propiedades.com/inmuebles/local-en-renta-calle-de-la-fuente-235-235-monclova-centro-coahuila-29766701",
    "Lat": "26.9014325",
    "Lng": "-101.4198291"
  },
  {
    "Título": "Local en Ignacio Zaragoza 109 #109, Col. Monclova Centro C.P. 25700, Monclova",
    "Precio": 50000,
    "Ubicación": "Ignacio Zaragoza 109 #109, Col. Monclova Centro C.P. 25700, Monclova",
    "Superficie": 385,
    "Enlace": "https://propiedades.com/inmuebles/local-en-renta-ignacio-zaragoza-109-109-monclova-centro-coahuila-28659876",
    "Lat": "26.901696496586357",
    "Lng": "-101.41669088280334"
  }
]