[
  {
    "Título": "Local en  , Col. Piedras Negras Centro C.P. 26000, Piedras Negras",
    "Precio": 2350000,
    "Ubicación": " , Col. Piedras Negras Centro C.P. 26000, Piedras Negras",
    "Superficie": 99,
    "Enlace": "https://propiedades.com/inmuebles/local-en-venta-piedras-negras-centro-coahuila-28082507",
    "Lat": "28.6915581",
    "Lng": "-100.5408985"
  },
  {
    "Título": "Local en ave emilio carranza #1213, Col. Buenavista Norte C.P. 26040, Piedras Negras",
    "Precio": 40000000,
    "Ubicación": "ave emilio carranza #1213, Col. Buenavista Norte C.P. 26040, Piedras Negras",
    "Superficie": 2080,
    "Enlace": "https://propiedades.com/inmuebles/local-en-venta-ave-emilio-carranza-1213-buenavista-norte-coahuila-28823179",
    "Lat": "28.695349508859564",
    "Lng": "-100.53151461636352"
  }
]