[
  {
    "Título": "Terreno comercial en Alemania 86 2804 #2804, Col. México 86 C.P. 67194, Guadalupe",
    "Precio": 60000,
    "Ubicación": "Alemania 86 2804 #2804, Col. México 86 C.P. 67194, Guadalupe",
    "Superficie": 1240,
    "Enlace": "https://propiedades.com/inmuebles/terreno-comercial-en-renta-alemania-86-2804-2804-mexico-86-nuevo_leon-28643605",
    "Lat": "25.651696825012984",
    "Lng": "-100.19953409874189"
  },
  {
    "Título": "Terreno comercial en ELOY CAVAZOS, Col. Mirador de la Silla C.P. 67176, Guadalupe",
    "Precio": 40000,
    "Ubicación": "ELOY CAVAZOS, Col. Mirador de la Silla C.P. 67176, Guadalupe",
    "Superficie": 302,
    "Enlace": "https://propiedades.com/inmuebles/terreno-comercial-en-renta-eloy-cavazos-mirador-de-la-silla-nuevo_leon-26855090",
    "Lat": "25.6615825000",
    "Lng": "-100.2362468000"
  },
  {
    "Título": "Terreno comercial en Avenida Miguel Aleman 4401 #4401Int. 4401, Col. Valle de las Flores C.P. 67130, Guadalupe",
    "Precio": 3000,
    "Ubicación": "Avenida Miguel Aleman 4401 #4401Int. 4401, Col. Valle de las Flores C.P. 67130, Guadalupe",
    "Superficie": 1000,
    "Enlace": "https://propiedades.com/inmuebles/terreno-comercial-en-renta-avenida-miguel-aleman-4401-4401-valle-de-las-flores-nuevo_leon-26871875",
    "Lat": "25.689956896171388",
    "Lng": "-100.2543565821433"
  },
  {
    "Título": "Terreno comercial en  , Col. Campestre la Silla C.P. 67183, Guadalupe",
    "Precio": 50000,
    "Ubicación": " , Col. Campestre la Silla C.P. 67183, Guadalupe",
    "Superficie": 683,
    "Enlace": "https://propiedades.com/inmuebles/terreno-comercial-en-renta-campestre-la-silla-nuevo_leon-22565551",
    "Lat": "25.6474306",
    "Lng": "-100.2028968"
  },
  {
    "Título": "Terreno comercial en AVE. ACUEDUCTO #100, Col. Tierra Propia Sector 1 C.P. 67197, Guadalupe",
    "Precio": 90000,
    "Ubicación": "AVE. ACUEDUCTO #100, Col. Tierra Propia Sector 1 C.P. 67197, Guadalupe",
    "Superficie": 2000,
    "Enlace": "https://propiedades.com/inmuebles/terreno-comercial-en-renta-ave-acueducto-100-tierra-propia-sector-1-nuevo_leon-29173352",
    "Lat": "25.6394698",
    "Lng": "-100.180863"
  }
]